vorak/__init__.py
vorak/__main__.py
vorak/cli.py
vorak/agents/__init__.py
vorak/agents/tester.py
vorak/core/analyzer.py
vorak/core/comparison.py
vorak/core/connectors.py
vorak/core/governance.py
vorak/core/models.py
vorak/core/plugins.py
vorak/core/prompt_generator.py
vorak/core/prompt_manager.py
vorak/core/reporting.py
vorak/core/database/__init__.py
vorak/core/database/manager.py
vorak/core/evaluators/__init__.py
vorak/core/evaluators/agent_reasoning.py
vorak/core/evaluators/base.py
vorak/core/evaluators/code_security.py
vorak/core/evaluators/pii.py
vorak/core/evaluators/sandbox.py
vorak/core/evaluators/secrets.py
vorak/prompts/__init__.py
vorak/prompts/advanced_prompts.json
vorak/prompts/prompt_library.json
vorak/web_interface/Home.py
vorak/web_interface/launcher.py
vorak/web_interface/pages/1_Security_Dashboard.py
vorak/web_interface/pages/2_Compare_Sessions.py
vorak-1.0.6.dist-info/licenses/LICENSE.txt
vorak-1.0.6.dist-info/METADATA
vorak-1.0.6.dist-info/WHEEL
vorak-1.0.6.dist-info/entry_points.txt
vorak-1.0.6.dist-info/top_level.txt
vorak-1.0.6.dist-info/RECORD
