Metadata-Version: 2.4
Name: vorak
Version: 1.0.6
Summary: Vulnerability Oriented Red-teaming for AI Knowledge
Author-email: Ruchir Kulkarni <ruchirkulkarni22@gmail.com>
Project-URL: Homepage, https://github.com/ruchirk22/vorak.git
Project-URL: Bug Tracker, https://github.com/ruchirk22/vorak/issues
Classifier: Programming Language :: Python :: 3
Classifier: License :: OSI Approved :: Apache Software License
Classifier: Operating System :: OS Independent
Classifier: Topic :: Scientific/Engineering :: Artificial Intelligence
Classifier: Topic :: Security
Requires-Python: >=3.9
License-File: LICENSE.txt
Requires-Dist: typer
Requires-Dist: rich
Requires-Dist: plotly
Requires-Dist: pandas
Requires-Dist: google-generativeai
Requires-Dist: openai
Requires-Dist: anthropic
Requires-Dist: python-dotenv
Requires-Dist: requests
Requires-Dist: fpdf2
Requires-Dist: streamlit
Requires-Dist: kaleido
Requires-Dist: bandit
Requires-Dist: nlpaug
Requires-Dist: textattack
Requires-Dist: seaborn
Requires-Dist: pyyaml
Provides-Extra: local
Requires-Dist: transformers; extra == "local"
Requires-Dist: torch; extra == "local"
Dynamic: license-file
